reline/__init__.py
reline/main.py
reline/nodes/__init__.py
reline/nodes/registry.py
reline/nodes/cvt_color/__init__.py
reline/nodes/cvt_color/node.py
reline/nodes/file_reader/__init__.py
reline/nodes/file_reader/node.py
reline/nodes/file_writer/__init__.py
reline/nodes/file_writer/node.py
reline/nodes/folder_reader/__init__.py
reline/nodes/folder_reader/node.py
reline/nodes/folder_writer/__init__.py
reline/nodes/folder_writer/node.py
reline/nodes/halftone/__init__.py
reline/nodes/halftone/_halftone_func.py
reline/nodes/halftone/node.py
reline/nodes/level/__init__.py
reline/nodes/level/node.py
reline/nodes/resize/__init__.py
reline/nodes/resize/filter_type.py
reline/nodes/resize/node.py
reline/nodes/sharp/__init__.py
reline/nodes/sharp/_sharp_class.py
reline/nodes/sharp/node.py
reline/nodes/upscale/__init__.py
reline/nodes/upscale/node.py
reline/pipeline/__init__.py
reline/pipeline/pipeline.py
reline/static/__init__.py
reline/static/file.py
reline/static/node.py
reline-1.2.3.dist-info/METADATA
reline-1.2.3.dist-info/WHEEL
reline-1.2.3.dist-info/entry_points.txt
reline-1.2.3.dist-info/licenses/LICENSE
reline-1.2.3.dist-info/RECORD
