Metadata-Version: 2.4
Name: reline
Version: 1.2.3
License-Expression: MIT
License-File: LICENSE
Requires-Python: >=3.10
Requires-Dist: moviepy==1.0.2
Requires-Dist: opencv-python-headless>=4.11.0.86
Requires-Dist: orjson>=3.10.15
Requires-Dist: pepeline>=1.0.2
Requires-Dist: resr<2,>=1
Requires-Dist: resselt<2,>=1
Requires-Dist: tqdm>=4.67.1
Requires-Dist: typer>=0.15.4
